fastapi_agentrouter/__init__.py
fastapi_agentrouter/__main__.py
fastapi_agentrouter/agents/__init__.py
fastapi_agentrouter/agents/vertexai/__init__.py
fastapi_agentrouter/agents/vertexai/dependencies.py
fastapi_agentrouter/core/__init__.py
fastapi_agentrouter/core/dependencies.py
fastapi_agentrouter/core/routers.py
fastapi_agentrouter/core/settings.py
fastapi_agentrouter/integrations/__init__.py
fastapi_agentrouter/integrations/slack/__init__.py
fastapi_agentrouter/integrations/slack/dependencies.py
fastapi_agentrouter/integrations/slack/router.py
fastapi_agentrouter-0.6.4.dist-info/METADATA
fastapi_agentrouter-0.6.4.dist-info/WHEEL
fastapi_agentrouter-0.6.4.dist-info/licenses/LICENSE
fastapi_agentrouter-0.6.4.dist-info/RECORD
