Metadata-Version: 2.4
Name: fastapi-agentrouter
Version: 0.6.4
Summary: AI Agent interface library for FastAPI with multi-platform support
Project-URL: Homepage, https://github.com/chanyou0311/fastapi-agentrouter
Project-URL: Documentation, https://chanyou0311.github.io/fastapi-agentrouter
Project-URL: Repository, https://github.com/chanyou0311/fastapi-agentrouter
Project-URL: Bug Tracker, https://github.com/chanyou0311/fastapi-agentrouter/issues
Project-URL: Changelog, https://github.com/chanyou0311/fastapi-agentrouter/releases
Author-email: Yu Nakamura <chanyou0311@gmail.com>
License: MIT
License-File: LICENSE
Keywords: agent,ai,discord,fastapi,slack,webhook
Classifier: Development Status :: 4 - Beta
Classifier: Framework :: FastAPI
Classifier: Intended Audience :: Developers
Classifier: License :: OSI Approved :: MIT License
Classifier: Operating System :: OS Independent
Classifier: Programming Language :: Python :: 3
Classifier: Programming Language :: Python :: 3.10
Classifier: Programming Language :: Python :: 3.11
Classifier: Programming Language :: Python :: 3.12
Classifier: Topic :: Internet :: WWW/HTTP :: WSGI :: Application
Classifier: Topic :: Software Development :: Libraries :: Python Modules
Requires-Python: >=3.10
Requires-Dist: fastapi>=0.100.0
Requires-Dist: pydantic-settings>=2.0.0
Requires-Dist: pydantic>=2.0.0
Provides-Extra: all
Requires-Dist: google-cloud-aiplatform>=1.38.0; extra == 'all'
Requires-Dist: pynacl>=1.5.0; extra == 'all'
Requires-Dist: slack-bolt>=1.14.0; extra == 'all'
Provides-Extra: dev
Requires-Dist: fastapi[standard]>=0.116.1; extra == 'dev'
Requires-Dist: httpx>=0.24.0; extra == 'dev'
Requires-Dist: mypy>=1.5.0; extra == 'dev'
Requires-Dist: pre-commit>=3.0.0; extra == 'dev'
Requires-Dist: pytest-asyncio>=0.21.0; extra == 'dev'
Requires-Dist: pytest-cov>=4.0.0; extra == 'dev'
Requires-Dist: pytest>=7.0.0; extra == 'dev'
Requires-Dist: ruff>=0.9.0; extra == 'dev'
Requires-Dist: types-requests; extra == 'dev'
Provides-Extra: discord
Requires-Dist: pynacl>=1.5.0; extra == 'discord'
Provides-Extra: docs
Requires-Dist: mkdocs-autorefs>=0.4.0; extra == 'docs'
Requires-Dist: mkdocs-material>=9.0.0; extra == 'docs'
Requires-Dist: mkdocs-static-i18n>=1.2.0; extra == 'docs'
Requires-Dist: mkdocstrings[python]>=0.22.0; extra == 'docs'
Provides-Extra: slack
Requires-Dist: slack-bolt>=1.14.0; extra == 'slack'
Provides-Extra: vertexai
Requires-Dist: google-cloud-aiplatform>=1.38.0; extra == 'vertexai'
